pub_ready_plots-1.2.3.dist-info/METADATA
pub_ready_plots-1.2.3.dist-info/WHEEL
pub_ready_plots-1.2.3.dist-info/entry_points.txt
pub_ready_plots-1.2.3.dist-info/licenses/LICENSE
pub_ready_plots/.DS_Store
pub_ready_plots/__init__.py
pub_ready_plots/pub_ready_plots.py
pub_ready_plots/styles.py
pub_ready_plots-1.2.3.dist-info/RECORD
