Metadata-Version: 2.1
Name: pub-ready-plots
Version: 1.2.3
Summary: Easy publication-ready matplotlib plots for ML papers and posters.
Author-Email: Agustinus Kristiadi <agustinus@kristia.de>
License: MIT
Classifier: License :: OSI Approved :: MIT License
Classifier: Operating System :: OS Independent
Classifier: Programming Language :: Python :: 3.9
Requires-Python: >=3.9
Requires-Dist: matplotlib>=3.9.0
